ExcelLibrary.py
robotframework_excellib-2.0.1.dist-info/LICENSE
robotframework_excellib-2.0.1.dist-info/METADATA
robotframework_excellib-2.0.1.dist-info/WHEEL
robotframework_excellib-2.0.1.dist-info/top_level.txt
robotframework_excellib-2.0.1.dist-info/RECORD
