Metadata-Version: 1.1
Name: robotframework-excellib
Version: 2.0.1
Summary: Robot Framework library for working with Excel documents
Home-page: https://github.com/peterservice-rnd/robotframework-excellib
Author: Nexign
Author-email: MF_AIST_all@nexign-systems.com
License: Apache License 2.0
Keywords: testing testautomation robotframework excel
Platform: UNKNOWN
Classifier: Development Status :: 5 - Production/Stable
Classifier: Intended Audience :: Developers
Classifier: Topic :: Software Development :: Testing
Classifier: License :: OSI Approved :: Apache Software License
Classifier: Programming Language :: Python :: 3.5
Classifier: Programming Language :: Python :: 3.6
Classifier: Framework :: Robot Framework :: Library
